MANIFEST.in
README.rst
setup.py
odbm/__init__.py
odbm.egg-info/PKG-INFO
odbm.egg-info/SOURCES.txt
odbm.egg-info/dependency_links.txt
odbm.egg-info/top_level.txt