Metadata-Version: 1.0
Name: odbm
Version: 0.5.6
Summary: Object wrapper for dbms
Home-page: http://bitbucket.org/imbolc/odbm/
Author: Imbolc
Author-email: imbolc@imbolc.name
License: BSD
Keywords: dbm
Platform: UNKNOWN
Classifier: Development Status :: 4 - Beta
Classifier: License :: OSI Approved :: BSD License
Classifier: Operating System :: OS Independent
Classifier: Programming Language :: Python
Classifier: Topic :: Software Development :: Libraries :: Python Modules
